namez/__init__.py
namez/namez.py
namez/typez.py
namez-0.3.0.dist-info/LICENSE
namez-0.3.0.dist-info/WHEEL
namez-0.3.0.dist-info/METADATA
namez-0.3.0.dist-info/RECORD
