Metadata-Version: 2.1
Name: namez
Version: 0.3.0
Summary: A package for accessing objects by name
Home-page: https://github.com/shawwn/namez
License: MIT
Author: Shawn Presser
Requires-Python: >=3.8,<4.0
Classifier: License :: OSI Approved :: MIT License
Classifier: Programming Language :: Python :: 3
Classifier: Programming Language :: Python :: 3.8
Classifier: Programming Language :: Python :: 3.9
Classifier: Programming Language :: Python :: 3.10
